{"timestamp":"2021-12-31T03:08:53.3132766Z","payload":{"OutputEvents":0.0,"OutputEventsPerSecond":0.0,"OutputWatermarkDelaySeconds":5.8595834,"OutputEventsSerializerErrors":0.0,"OutputEventsSerializerErrorsPerSecond":0.0}}
{"timestamp":"2021-12-31T03:09:03.3022776Z","payload":{"OutputEvents":0.0,"OutputEventsPerSecond":0.0,"OutputWatermarkDelaySeconds":6.319812600000001,"OutputEventsSerializerErrors":0.0,"OutputEventsSerializerErrorsPerSecond":0.0}}
{"timestamp":"2021-12-31T03:09:13.3068525Z","payload":{"OutputEvents":0.0,"OutputEventsPerSecond":0.0,"OutputWatermarkDelaySeconds":5.6767620999999995,"OutputEventsSerializerErrors":0.0,"OutputEventsSerializerErrorsPerSecond":0.0}}
{"timestamp":"2021-12-31T03:09:23.3024412Z","payload":{"OutputEvents":0.0,"OutputEventsPerSecond":0.0,"OutputWatermarkDelaySeconds":6.1171254,"OutputEventsSerializerErrors":0.0,"OutputEventsSerializerErrorsPerSecond":0.0}}
{"timestamp":"2021-12-31T03:09:33.2956477Z","payload":{"OutputEvents":0.0,"OutputEventsPerSecond":0.0,"OutputWatermarkDelaySeconds":5.8285556,"OutputEventsSerializerErrors":0.0,"OutputEventsSerializerErrorsPerSecond":0.0}}
{"timestamp":"2021-12-31T03:09:43.300162Z","payload":{"OutputEvents":3.0,"OutputEventsPerSecond":3.0,"OutputWatermarkDelaySeconds":5.9126005,"OutputEventsSerializerErrors":0.0,"OutputEventsSerializerErrorsPerSecond":0.0}}
{"timestamp":"2021-12-31T03:09:52.2879108Z","payload":{"OutputEvents":9.0,"OutputEventsPerSecond":9.0,"OutputWatermarkDelaySeconds":5.8062957,"OutputEventsSerializerErrors":0.0,"OutputEventsSerializerErrorsPerSecond":0.0}}
