{"timestamp":"2021-12-30T18:34:30.4381782Z","payload":{"QueryWatermarkDelaySeconds":2.5061662}}
{"timestamp":"2021-12-30T18:34:40.4347518Z","payload":{"QueryWatermarkDelaySeconds":2.4748257}}
{"timestamp":"2021-12-30T18:34:50.4420665Z","payload":{"QueryWatermarkDelaySeconds":3.4391987}}
{"timestamp":"2021-12-30T18:35:00.4378809Z","payload":{"QueryWatermarkDelaySeconds":2.2216692}}
{"timestamp":"2021-12-30T18:35:10.4614734Z","payload":{"QueryWatermarkDelaySeconds":2.4428573}}
{"timestamp":"2021-12-30T18:35:20.4442561Z","payload":{"QueryWatermarkDelaySeconds":2.0945364}}
{"timestamp":"2021-12-30T18:35:30.4412041Z","payload":{"QueryWatermarkDelaySeconds":2.4485467}}
{"timestamp":"2021-12-30T18:35:40.4397145Z","payload":{"QueryWatermarkDelaySeconds":2.4462292000000003}}
{"timestamp":"2021-12-30T18:35:50.4438295Z","payload":{"QueryWatermarkDelaySeconds":3.4438422999999996}}
{"timestamp":"2021-12-30T18:36:00.434258Z","payload":{"QueryWatermarkDelaySeconds":2.4473547}}
{"timestamp":"2021-12-30T18:36:10.4561987Z","payload":{"QueryWatermarkDelaySeconds":2.1214754}}
{"timestamp":"2021-12-30T18:36:20.4366306Z","payload":{"QueryWatermarkDelaySeconds":3.4612257}}
{"timestamp":"2021-12-30T18:36:30.4441515Z","payload":{"QueryWatermarkDelaySeconds":2.0241771}}
{"timestamp":"2021-12-30T18:36:40.4382811Z","payload":{"QueryWatermarkDelaySeconds":2.4483018000000003}}
{"timestamp":"2021-12-30T18:36:50.4489602Z","payload":{"QueryWatermarkDelaySeconds":3.4417522}}
{"timestamp":"2021-12-30T18:37:00.4470373Z","payload":{"QueryWatermarkDelaySeconds":2.4533104}}
{"timestamp":"2021-12-30T18:37:10.4420734Z","payload":{"QueryWatermarkDelaySeconds":2.2266046}}
{"timestamp":"2021-12-30T18:37:20.4372314Z","payload":{"QueryWatermarkDelaySeconds":2.4498137}}
{"timestamp":"2021-12-30T18:37:30.4483186Z","payload":{"QueryWatermarkDelaySeconds":2.4422268}}
{"timestamp":"2021-12-30T18:37:40.4420994Z","payload":{"QueryWatermarkDelaySeconds":1.9222302999999998}}
{"timestamp":"2021-12-30T18:37:50.4388661Z","payload":{"QueryWatermarkDelaySeconds":2.4507493}}
{"timestamp":"2021-12-30T18:38:00.454977Z","payload":{"QueryWatermarkDelaySeconds":2.4447162}}
{"timestamp":"2021-12-30T18:38:10.4344131Z","payload":{"QueryWatermarkDelaySeconds":3.4666655}}
{"timestamp":"2021-12-30T18:38:11.8891392Z","payload":{"QueryWatermarkDelaySeconds":2.4179596}}
